queuebytesio/__init__.py
queue_bytes_io-0.1.0.dist-info/LICENSE
queue_bytes_io-0.1.0.dist-info/METADATA
queue_bytes_io-0.1.0.dist-info/WHEEL
queue_bytes_io-0.1.0.dist-info/top_level.txt
queue_bytes_io-0.1.0.dist-info/RECORD
